{
  "timestamp": "2026-02-13T02:28:39+06:30",
  "title": "BTC Market Pulse: $65,882 (-2.45%)",
  "summary": "Spot ~$65,882; 24h: -2.45%; 24h range: $65,243–$68,309; Momentum is pulling back on the day.",
  "prediction": "Short-term bias: neutral-to-bearish while below the first resistance. A reclaim and hold above resistance could flip momentum bullish. A breakdown below the first support increases odds of a deeper pullback toward the next support zone.",
  "support": [
    64250,
    65200
  ],
  "resistance": [
    68300,
    69250
  ]
}
